strictdataclass/__init__.py
strictdataclass-0.1.0.dist-info/METADATA
strictdataclass-0.1.0.dist-info/WHEEL
strictdataclass-0.1.0.dist-info/licenses/LICENSE
strictdataclass-0.1.0.dist-info/RECORD
