Metadata-Version: 2.1
Name: strictdataclass
Version: 0.1.0
Summary: Auto type cast dataclasses to suggested types.
Project-URL: Homepage, https://github.com/Braden2n/StrictDataclass
Project-URL: Documentation, https://github.com/Braden2n/StrictDataclass
Project-URL: Issues, https://github.com/Braden2n/StrictDataclass/issues
Project-URL: Repository, https://github.com
Project-URL: Changelog, https://github.com/Braden2n/StrictDataclass/activity
Author-email: Braden Toone <braden@toonetown.com>
Maintainer-email: Braden Toone <braden@toonetown.com>
License: MIT License
License-File: LICENSE
Keywords: cast,dataclass,inherit,strict,type
Classifier: Development Status :: 4 - Beta
Classifier: Intended Audience :: Developers
Classifier: License :: OSI Approved :: MIT License
Classifier: Natural Language :: English
Classifier: Operating System :: OS Independent
Classifier: Programming Language :: Python :: 3.7
Classifier: Topic :: Software Development :: Libraries :: Python Modules
Requires-Python: >=3.7
Requires-Dist: any-cast>=0.0.3
Requires-Dist: instancemethod>=1.5
